sendgrid/__init__.py
sendgrid/base_interface.py
sendgrid/sendgrid.py
sendgrid/twilio_email.py
sendgrid/version.py
sendgrid/helpers/__init__.py
sendgrid/helpers/endpoints/__init__.py
sendgrid/helpers/endpoints/ip/__init__.py
sendgrid/helpers/endpoints/ip/unassigned.py
sendgrid/helpers/eventwebhook/__init__.py
sendgrid/helpers/eventwebhook/eventwebhook_header.py
sendgrid/helpers/inbound/__init__.py
sendgrid/helpers/inbound/app.py
sendgrid/helpers/inbound/config.py
sendgrid/helpers/inbound/config.yml
sendgrid/helpers/inbound/parse.py
sendgrid/helpers/inbound/send.py
sendgrid/helpers/inbound/sample_data/default_data.txt
sendgrid/helpers/inbound/sample_data/default_data_with_attachments.txt
sendgrid/helpers/inbound/sample_data/raw_data.txt
sendgrid/helpers/inbound/sample_data/raw_data_with_attachments.txt
sendgrid/helpers/mail/__init__.py
sendgrid/helpers/mail/amp_html_content.py
sendgrid/helpers/mail/asm.py
sendgrid/helpers/mail/attachment.py
sendgrid/helpers/mail/batch_id.py
sendgrid/helpers/mail/bcc_email.py
sendgrid/helpers/mail/bcc_settings.py
sendgrid/helpers/mail/bcc_settings_email.py
sendgrid/helpers/mail/bypass_bounce_management.py
sendgrid/helpers/mail/bypass_list_management.py
sendgrid/helpers/mail/bypass_spam_management.py
sendgrid/helpers/mail/bypass_unsubscribe_management.py
sendgrid/helpers/mail/category.py
sendgrid/helpers/mail/cc_email.py
sendgrid/helpers/mail/click_tracking.py
sendgrid/helpers/mail/content.py
sendgrid/helpers/mail/content_id.py
sendgrid/helpers/mail/custom_arg.py
sendgrid/helpers/mail/disposition.py
sendgrid/helpers/mail/dynamic_template_data.py
sendgrid/helpers/mail/email.py
sendgrid/helpers/mail/exceptions.py
sendgrid/helpers/mail/file_content.py
sendgrid/helpers/mail/file_name.py
sendgrid/helpers/mail/file_type.py
sendgrid/helpers/mail/footer_html.py
sendgrid/helpers/mail/footer_settings.py
sendgrid/helpers/mail/footer_text.py
sendgrid/helpers/mail/from_email.py
sendgrid/helpers/mail/ganalytics.py
sendgrid/helpers/mail/group_id.py
sendgrid-6.12.4.dist-info/LICENSE
sendgrid-6.12.4.dist-info/METADATA
sendgrid-6.12.4.dist-info/WHEEL
sendgrid-6.12.4.dist-info/top_level.txt
sendgrid-6.12.4.dist-info/RECORD
